README.txt
setup.py
gxs700/__init__.py
gxs700/fpga.py
gxs700/fw.py
gxs700/fw_lg.py
gxs700/fw_sm.py
gxs700/usbint.py
gxs700/util.py
gxs700.egg-info/PKG-INFO
gxs700.egg-info/SOURCES.txt
gxs700.egg-info/dependency_links.txt
gxs700.egg-info/requires.txt
gxs700.egg-info/top_level.txt