Metadata-Version: 1.1
Name: gxs700
Version: 1.0.0
Summary: Gendex GXS700 / Dexis Platinum USB x-ray sensor driver.
Home-page: https://github.com/JohnDMcMaster/gxs700
Author: John McMaster
Author-email: JohnDMcMaster@gmail.com
License: BSD
Keywords: gxs700 gendex dexis x-ray
Platform: UNKNOWN
Classifier: License :: OSI Approved :: BSD License
